nicesql/__init__.py
nicesql/db/__init__.py
nicesql/db/_driver.py
nicesql/db/_driver_mysql.py
nicesql/db/_driver_sqlite.py
nicesql/db/_execute.py
nicesql/db/_register.py
nicesql/db/_result.py
nicesql/db/_sqlconv.py
nicesql/shortcut/__init__.py
nicesql/shortcut/_base.py
nicesql/shortcut/_delete.py
nicesql/shortcut/_insert.py
nicesql/shortcut/_select.py
nicesql/shortcut/_update.py
nicesql/shortcut/_utils.py
nicesql/utils/__init__.py
nicesql/utils/_logger.py
nicesql/utils/_tls.py
nice_sql-3.0.2.dist-info/METADATA
nice_sql-3.0.2.dist-info/WHEEL
nice_sql-3.0.2.dist-info/top_level.txt
nice_sql-3.0.2.dist-info/RECORD
