Metadata-Version: 2.1
Name: nice-sql
Version: 3.0.2
Summary: easy/lite/simple db query for python db api 2.0
Home-page: https://github.com/minusli/nicesql
Author: minusli
Author-email: minusli@foxmail.com
License: Apache License 2.0
Platform: UNKNOWN
Requires-Python: >=3
Requires-Dist: pytest
Requires-Dist: pymysql
Requires-Dist: DBUtils
Requires-Dist: dsnparse
Requires-Dist: nice-datapath (==0.0.1)
